<?xml version="1.0"?>
<opencv_storage>
<stage1>
  <maxWeakCount>58</maxWeakCount>
  <stageThreshold>-8.0216741561889648e-01</stageThreshold>
  <weakClassifiers>
    <_>
      <internalNodes>
        0 -1 5179 1.1455923318862915e-02</internalNodes>
      <leafValues>
        -3.0919447541236877e-01 7.4293226003646851e-01</leafValues></_>
    <_>
      <internalNodes>
        0 -1 26049 -3.6493008956313133e-03</internalNodes>
      <leafValues>
        4.2731702327728271e-01 -5.3350430727005005e-01</leafValues></_>
    <_>
      <internalNodes>
        0 -1 1190 7.9752842430025339e-04</internalNodes>
      <leafValues>
        -5.7438957691192627e-01 2.4737285077571869e-01</leafValues></_>
    <_>
      <internalNodes>
        0 -1 26290 5.0343032926321030e-03</internalNodes>
      <leafValues>
        1.7813025414943695e-01 -7.8674221038818359e-01</leafValues></_>
    <_>
      <internalNodes>
        0 -1 31375 -3.3826357126235962e-01</internalNodes>
      <leafValues>
        -8.3020240068435669e-01 1.2336488813161850e-01</leafValues></_>
    <_>
      <internalNodes>
        0 -1 60441 9.7455870127305388e-04</internalNodes>
      <leafValues>
        -2.4122472107410431e-01 5.1170027256011963e-01</leafValues></_>
    <_>
      <internalNodes>
        0 -1 5853 7.7368703205138445e-04</internalNodes>
      <leafValues>
        -4.1549661755561829e-01 2.4740631878376007e-01</leafValues></_>
    <_>
      <internalNodes>
        0 -1 49877 -2.9199561104178429e-03</internalNodes>
      <leafValues>
        -7.5562584400177002e-01 1.5149071812629700e-01</leafValues></_>
    <_>
      <internalNodes>
        0 -1 50321 -6.5261885523796082e-02</internalNodes>
      <leafValues>
        1.1173264682292938e-01 -6.8139117956161499e-01</leafValues></_>
    <_>
      <internalNodes>
        0 -1 948 -2.5677274912595749e-02</internalNodes>
      <leafValues>
        -6.8820691108703613e-01 1.1594139039516449e-01</leafValues></_>
    <_>
      <internalNodes>
        0 -1 14512 -1.2404778972268105e-03</internalNodes>
      <leafValues>
        2.2905495762825012e-01 -4.0870717167854309e-01</leafValues></_>
    <_>
      <internalNodes>
        0 -1 118864 6.0073798522353172e-03</internalNodes>
      <leafValues>
        1.5175445377826691e-01 -5.2299404144287109e-01</leafValues></_>
    <_>
      <internalNodes>
        0 -1 38461 2.9311659745872021e-03</internalNodes>
      <leafValues>
        9.1342732310295105e-02 -7.7701073884963989e-01</leafValues></_>
    <_>
      <internalNodes>
        0 -1 71558 -5.0610015168786049e-03</internalNodes>
      <leafValues>
        7.4438023567199707e-01 -1.2657904624938965e-01</leafValues></_>
    <_>
      <internalNodes>
        0 -1 51227 -1.9416131544858217e-03</internalNodes>
      <leafValues>
        5.0292116403579712e-01 -1.7826455831527710e-01</leafValues></_>
    <_>
      <internalNodes>
        0 -1 30356 1.8423176370561123e-03</internalNodes>
      <leafValues>
        1.0941039770841599e-01 -7.7295714616775513e-01</leafValues></_>
    <_>
      <internalNodes>
        0 -1 27832 -1.6387350857257843e-02</internalNodes>
      <leafValues>
        -7.7265346050262451e-01 9.5862798392772675e-02</leafValues></_>
    <_>
      <internalNodes>
        0 -1 5958 1.3042330741882324e-02</internalNodes>
      <leafValues>
        -1.3272006809711456e-01 6.6880059242248535e-01</leafValues></_>
    <_>
      <internalNodes>
        0 -1 19623 -1.5325199346989393e-03</internalNodes>
      <leafValues>
        4.3133914470672607e-01 -2.0221574604511261e-01</leafValues></_>
    <_>
      <internalNodes>
        0 -1 5936 -6.0397391207516193e-03</internalNodes>
      <leafValues>
        -4.8568630218505859e-01 1.5634363889694214e-01</leafValues></_>
    <_>
      <internalNodes>
        0 -1 151821 -1.4430581359192729e-03</internalNodes>
      <leafValues>
        -5.0757932662963867e-01 1.3700808584690094e-01</leafValues></_>
    <_>
      <internalNodes>
        0 -1 28764 2.6149661280214787e-03</internalNodes>
      <leafValues>
        1.2398533523082733e-01 -5.6391221284866333e-01</leafValues></_>
    <_>
      <internalNodes>
        0 -1 52118 4.0506161749362946e-03</internalNodes>
      <leafValues>
        -1.8482483923435211e-01 4.2166763544082642e-01</leafValues></_>
    <_>
      <internalNodes>
        0 -1 37931 -6.2184803187847137e-02</internalNodes>
      <leafValues>
        -5.0787210464477539e-01 1.4239521324634552e-01</leafValues></_>
    <_>
      <internalNodes>
        0 -1 28710 -1.0453332960605621e-01</internalNodes>
      <leafValues>
        2.7826526761054993e-01 -3.3313918113708496e-01</leafValues></_>
    <_>
      <internalNodes>
        0 -1 5009 2.0173622760921717e-03</internalNodes>
      <leafValues>
        1.0859302431344986e-01 -6.4470356702804565e-01</leafValues></_>
    <_>
      <internalNodes>
        0 -1 80779 6.9694416597485542e-03</internalNodes>
      <leafValues>
        -1.1852134019136429e-01 6.3478624820709229e-01</leafValues></_>
    <_>
      <internalNodes>
        0 -1 7418 -9.2468317598104477e-04</internalNodes>
      <leafValues>
        -6.4689117670059204e-01 1.1995407938957214e-01</leafValues></_>
    <_>
      <internalNodes>
        0 -1 102382 1.9199558300897479e-03</internalNodes>
      <leafValues>
        9.1850861907005310e-02 -6.6784286499023438e-01</leafValues></_>
    <_>
      <internalNodes>
        0 -1 25818 1.1821596417576075e-03</internalNodes>
      <leafValues>
        -1.6118732094764709e-01 3.9147949218750000e-01</leafValues></_>
    <_>
      <internalNodes>
        0 -1 174 -7.0582898333668709e-03</internalNodes>
      <leafValues>
        3.3185747265815735e-01 -2.1674463152885437e-01</leafValues></_>
    <_>
      <internalNodes>
        0 -1 51443 -8.4451055154204369e-03</internalNodes>
      <leafValues>
        -6.7247152328491211e-01 1.0405533760786057e-01</leafValues></_>
    <_>
      <internalNodes>
        0 -1 70959 -9.0909693390130997e-03</internalNodes>
      <leafValues>
        5.1245063543319702e-02 -9.7829347848892212e-01</leafValues></_>
    <_>
      <internalNodes>
        0 -1 145049 4.3236650526523590e-04</internalNodes>
      <leafValues>
        1.4052015542984009e-01 -3.9551317691802979e-01</leafValues></_>
    <_>
      <internalNodes>
        0 -1 72399 1.9839094951748848e-02</internalNodes>
      <leafValues>
        -7.1470372378826141e-02 8.3133029937744141e-01</leafValues></_>
    <_>
      <internalNodes>
        0 -1 1192 -8.3213865756988525e-02</internalNodes>
      <leafValues>
        -8.9568662643432617e-01 8.0836109817028046e-02</leafValues></_>
    <_>
      <internalNodes>
        0 -1 41494 -2.0630846265703440e-03</internalNodes>
      <leafValues>
        2.2442777454853058e-01 -2.6642349362373352e-01</leafValues></_>
    <_>
      <internalNodes>
        0 -1 70820 -1.9810482859611511e-02</internalNodes>
      <leafValues>
        7.1388101577758789e-01 -1.0040095448493958e-01</leafValues></_>
    <_>
      <internalNodes>
        0 -1 107257 -6.7465022206306458e-02</internalNodes>
      <leafValues>
        -5.8703351020812988e-01 1.2808565795421600e-01</leafValues></_>
    <_>
      <internalNodes>
        0 -1 12082 1.9445121288299561e-02</internalNodes>
      <leafValues>
        1.0516417771577835e-01 -5.2901595830917358e-01</leafValues></_>
    <_>
      <internalNodes>
        0 -1 6666 2.0903213880956173e-03</internalNodes>
      <leafValues>
        -1.4938019216060638e-01 4.2095255851745605e-01</leafValues></_>
    <_>
      <internalNodes>
        0 -1 30407 -5.8812517672777176e-03</internalNodes>
      <leafValues>
        6.9717341661453247e-01 -9.5982097089290619e-02</leafValues></_>
    <_>
      <internalNodes>
        0 -1 27821 -2.1184519864618778e-03</internalNodes>
      <leafValues>
        3.1197956204414368e-01 -2.3417527973651886e-01</leafValues></_>
    <_>
      <internalNodes>
        0 -1 14656 1.3023359701037407e-02</internalNodes>
      <leafValues>
        1.0034531354904175e-01 -6.8780410289764404e-01</leafValues></_>
    <_>
      <internalNodes>
        0 -1 3413 -1.7087377607822418e-02</internalNodes>
      <leafValues>
        -4.3029853701591492e-01 1.4084564149379730e-01</leafValues></_>
    <_>
      <internalNodes>
        0 -1 114733 -1.8430550117045641e-03</internalNodes>
      <leafValues>
        -5.1571238040924072e-01 1.1266789585351944e-01</leafValues></_>
    <_>
      <internalNodes>
        0 -1 60535 -5.6094639003276825e-03</internalNodes>
      <leafValues>
        3.8255020976066589e-01 -1.6108265519142151e-01</leafValues></_>
    <_>
      <internalNodes>
        0 -1 72389 2.9599646950373426e-05</internalNodes>
      <leafValues>
        -2.7695170044898987e-01 2.1436814963817596e-01</leafValues></_>
    <_>
      <internalNodes>
        0 -1 104008 -8.6849048733711243e-02</internalNodes>
      <leafValues>
        -6.5930402278900146e-01 8.8895387947559357e-02</leafValues></_>
    <_>
      <internalNodes>
        0 -1 157108 -3.7161687941988930e-05</internalNodes>
      <leafValues>
        2.3865999281406403e-01 -2.5550037622451782e-01</leafValues></_>
    <_>
      <internalNodes>
        0 -1 151866 1.0437066666781902e-03</internalNodes>
      <leafValues>
        1.0493187606334686e-01 -5.2740710973739624e-01</leafValues></_>
    <_>
      <internalNodes>
        0 -1 17175 4.8418011283501983e-04</internalNodes>
      <leafValues>
        8.8267095386981964e-02 -5.6951028108596802e-01</leafValues></_>
    <_>
      <internalNodes>
        0 -1 62079 -1.8974650884047151e-03</internalNodes>
      <leafValues>
        4.8913773894309998e-01 -1.4883786439895630e-01</leafValues></_>
    <_>
      <internalNodes>
        0 -1 103473 3.5298228263854980e-02</internalNodes>
      <leafValues>
        6.6618196666240692e-02 -9.1536438465118408e-01</leafValues></_>
    <_>
      <internalNodes>
        0 -1 49481 1.5627925749868155e-03</internalNodes>
      <leafValues>
        -1.2783852219581604e-01 4.7635018825531006e-01</leafValues></_>
    <_>
      <internalNodes>
        0 -1 19592 -3.9393529295921326e-03</internalNodes>
      <leafValues>
        -7.6573204994201660e-01 7.7958807349205017e-02</leafValues></_>
    <_>
      <internalNodes>
        0 -1 195 4.2536593973636627e-03</internalNodes>
      <leafValues>
        1.0099043697118759e-01 -4.9794521927833557e-01</leafValues></_>
    <_>
      <internalNodes>
        0 -1 3120 7.4225813150405884e-02</internalNodes>
      <leafValues>
        7.1532145142555237e-02 -6.6433602571487427e-01</leafValues></_></weakClassifiers></stage1>
</opencv_storage>
