<?xml version="1.0"?>
<opencv_storage>
<stage9>
  <maxWeakCount>29</maxWeakCount>
  <stageThreshold>-5.1533138751983643e-01</stageThreshold>
  <weakClassifiers>
    <_>
      <internalNodes>
        0 -1 3311 -16778241 -469762116 -4612 -515 -1633976325 1060174768
        252435707 2134891995</internalNodes>
      <leafValues>
        -1.6417910158634186e-01 6.5899777412414551e-01</leafValues></_>
    <_>
      <internalNodes>
        0 -1 1380 -723783256 -23391777 671623684 -227368934 -654087680
        1736802441 -2002013940 -168313957</internalNodes>
      <leafValues>
        -4.6553823351860046e-01 4.2033711075782776e-01</leafValues></_>
    <_>
      <internalNodes>
        0 -1 2670 -268435457 -67900172 2138267124 997412316 -13582856
        1043389680 2138103290 -8978562</internalNodes>
      <leafValues>
        -3.4768101572990417e-01 4.1744893789291382e-01</leafValues></_>
    <_>
      <internalNodes>
        0 -1 1589 1213104691 -461618872 1081687 -1291845310 -1968399705
        -2004188664 1101062641 1082718282</internalNodes>
      <leafValues>
        -6.3088428974151611e-01 2.0850697159767151e-01</leafValues></_>
    <_>
      <internalNodes>
        0 -1 14 -20671042 -268075005 -199866285 -1014939581 -1902581801
        -1978965760 537619179 -210797753</internalNodes>
      <leafValues>
        -3.5045602917671204e-01 3.8583397865295410e-01</leafValues></_>
    <_>
      <internalNodes>
        0 -1 5246 -141492428 -1793400638 1082938376 -138162062
        -889068699 34209880 285313609 -1059328978</internalNodes>
      <leafValues>
        -3.9422076940536499e-01 3.4050107002258301e-01</leafValues></_>
    <_>
      <internalNodes>
        0 -1 737 -1042840668 -1336585577 -1877938176 134875540
        -1862204677 1889345546 2286 2002774411</internalNodes>
      <leafValues>
        -4.3471857905387878e-01 2.9829037189483643e-01</leafValues></_>
    <_>
      <internalNodes>
        0 -1 164 -1022085725 1258688823 27849927 254249239 -1333282583
        2069602795 -1574802943 -213708093</internalNodes>
      <leafValues>
        -3.7534165382385254e-01 3.3078420162200928e-01</leafValues></_>
    <_>
      <internalNodes>
        0 -1 617 -665021524 -259783991 4427786 -2004111287 269595138
        1224773643 -651603456 885461814</internalNodes>
      <leafValues>
        -4.9215391278266907e-01 2.6267659664154053e-01</leafValues></_>
    <_>
      <internalNodes>
        0 -1 12 -1294322692 -1870567539 805372369 -2121398109 757485965
        136456344 690123028 1590565121</internalNodes>
      <leafValues>
        -6.8390887975692749e-01 1.9749306142330170e-01</leafValues></_>
    <_>
      <internalNodes>
        0 -1 467 910414830 1448219442 -788298898 -581004777 1112261472
        2089320458 1393858994 1956839809</internalNodes>
      <leafValues>
        -4.5456212759017944e-01 2.6286000013351440e-01</leafValues></_>
    <_>
      <internalNodes>
        0 -1 1444 796244917 -1346437185 1495134267 924581887 -26149
        -893485131 -552249125 -618725416</internalNodes>
      <leafValues>
        -2.8663951158523560e-01 4.4800826907157898e-01</leafValues></_>
    <_>
      <internalNodes>
        0 -1 6829 1502938624 949708827 -1601650392 -99041268 -1551244800
        -167559157 1524811808 -2019497206</internalNodes>
      <leafValues>
        -4.1998693346977234e-01 3.1670209765434265e-01</leafValues></_>
    <_>
      <internalNodes>
        0 -1 1673 -1820223199 -1539309484 269550611 -733740928
        -192810777 -1953533823 1428796661 1325633966</internalNodes>
      <leafValues>
        -4.9882772564888000e-01 2.6560989022254944e-01</leafValues></_>
    <_>
      <internalNodes>
        0 -1 2330 227012173 928452012 -817799896 -43498095 358302152
        196395584 1494115610 226476043</internalNodes>
      <leafValues>
        -3.7485280632972717e-01 3.8791531324386597e-01</leafValues></_>
    <_>
      <internalNodes>
        0 -1 503 1650221284 2070956043 -1325395837 -325303793 327278657
        838901890 -825404408 1691664520</internalNodes>
      <leafValues>
        -4.7937315702438354e-01 2.8952461481094360e-01</leafValues></_>
    <_>
      <internalNodes>
        0 -1 4469 1360785680 -1547448128 -2145920863 -589455085
        822321227 92569611 1342407857 275626602</internalNodes>
      <leafValues>
        -5.6615179777145386e-01 2.1880468726158142e-01</leafValues></_>
    <_>
      <internalNodes>
        0 -1 3878 1932035080 -1403756180 822346324 1652816676 404684098
        1036394664 304234512 353589319</internalNodes>
      <leafValues>
        -5.8889979124069214e-01 2.1875964105129242e-01</leafValues></_>
    <_>
      <internalNodes>
        0 -1 3288 -2010251237 427407631 -1207992452 -336513719
        -1145307278 -1213202514 355342687 -759793942</internalNodes>
      <leafValues>
        -3.1765919923782349e-01 4.2815253138542175e-01</leafValues></_>
    <_>
      <internalNodes>
        0 -1 2212 -1110221672 1549385017 2147016612 1601994509
        1609808114 -168921154 917911234 1932112327</internalNodes>
      <leafValues>
        -3.5354530811309814e-01 3.9242985844612122e-01</leafValues></_>
    <_>
      <internalNodes>
        0 -1 736 1910474188 1506066585 -1862089714 -799502206 -536149695
        33720576 -1693857620 -248026197</internalNodes>
      <leafValues>
        -4.1549754142761230e-01 3.2065257430076599e-01</leafValues></_>
    <_>
      <internalNodes>
        0 -1 2353 -1618962152 -1123385076 -738181053 -393412272
        690262502 -1333551104 235841566 523733452</internalNodes>
      <leafValues>
        -5.6872957944869995e-01 2.3751190304756165e-01</leafValues></_>
    <_>
      <internalNodes>
        0 -1 2869 1290358778 1227467448 1874107413 963929475 468168922
        -239635163 1876702908 -881207835</internalNodes>
      <leafValues>
        -3.3212918043136597e-01 3.9858308434486389e-01</leafValues></_>
    <_>
      <internalNodes>
        0 -1 3668 -784004844 1695925337 -922680888 -1195091556
        -254074108 549751938 -373163336 -1178787244</internalNodes>
      <leafValues>
        -4.2135772109031677e-01 3.1074610352516174e-01</leafValues></_>
    <_>
      <internalNodes>
        0 -1 2848 25887002 -291831339 -939523789 -863436452 1863006218
        -880107380 -1501003118 123242650</internalNodes>
      <leafValues>
        -5.9542614221572876e-01 2.3162665963172913e-01</leafValues></_>
    <_>
      <internalNodes>
        0 -1 1391 -1023739979 -1610530071 50482857 -1566965690
        -1574014339 -2143154143 671088705 -360166871</internalNodes>
      <leafValues>
        -5.6006199121475220e-01 2.3281753063201904e-01</leafValues></_>
    <_>
      <internalNodes>
        0 -1 273 1241175000 576266949 -1056224739 1230856979 -1153278571
        -418768740 -1491806109 -625885220</internalNodes>
      <leafValues>
        -3.6252993345260620e-01 3.8891592621803284e-01</leafValues></_>
    <_>
      <internalNodes>
        0 -1 2307 -177609123 -201326905 -1145097647 1929129196
        -572662422 -216137742 838625022 1818029261</internalNodes>
      <leafValues>
        -2.5864630937576294e-01 5.0786215066909790e-01</leafValues></_>
    <_>
      <internalNodes>
        0 -1 603 -1066223346 507838543 -770618970 496979982 4543119
        2003075202 -69174488 -470725773</internalNodes>
      <leafValues>
        -3.6201304197311401e-01 3.6847943067550659e-01</leafValues></_></weakClassifiers></stage9>
</opencv_storage>
